HISTORY.txt
LICENSE.txt
MANIFEST.in
README.rst
setup.py
.hg/last-message.txt
src/inqbus/__init__.py
src/inqbus.rainflow.egg-info/PKG-INFO
src/inqbus.rainflow.egg-info/SOURCES.txt
src/inqbus.rainflow.egg-info/dependency_links.txt
src/inqbus.rainflow.egg-info/entry_points.txt
src/inqbus.rainflow.egg-info/namespace_packages.txt
src/inqbus.rainflow.egg-info/not-zip-safe
src/inqbus.rainflow.egg-info/requires.txt
src/inqbus.rainflow.egg-info/top_level.txt
src/inqbus/rainflow/__init__.py
src/inqbus/rainflow/api.py
src/inqbus/rainflow/helpers.py
src/inqbus/rainflow/data_sources/__init__.py
src/inqbus/rainflow/data_sources/hdf5.py
src/inqbus/rainflow/examples/2017-06-06-Rainflow-Fehler.txt
src/inqbus/rainflow/examples/2017-06-06-rainflow_Moment_H211_0743.py
src/inqbus/rainflow/examples/2017-06-26-rainflow_Moment_H211_0743.py
src/inqbus/rainflow/examples/__init__.py
src/inqbus/rainflow/examples/create_hdf5_testfile.py
src/inqbus/rainflow/examples/example_custom.py
src/inqbus/rainflow/examples/example_hdf5.py
src/inqbus/rainflow/examples/example_numpy.py
src/inqbus/rainflow/rfc_base/__init__.py
src/inqbus/rainflow/rfc_base/classification.py
src/inqbus/rainflow/rfc_base/rainflow.pyx
src/inqbus/rainflow/rfc_base/rainflow.pyxbld
src/inqbus/rainflow/tests/__init__.py
src/inqbus/rainflow/tests/test_classification.py
src/inqbus/rainflow/tests/test_helpers.py