Metadata-Version: 1.1
Name: inqbus.rainflow
Version: 1.4
Summary: Cython optimized rainflow algorithm
Home-page: https://github.com/sandrarum/inqbus.rainflow
Author: volker.jaenisch@inqbus.de
Author-email: volker.jaenisch@inqbus.de
License: UNKNOWN
Keywords: rainflow
Platform: UNKNOWN
Classifier: Programming Language :: Python
Classifier: Environment :: Plugins
Classifier: Intended Audience :: System Administrators
Classifier: License :: Other/Proprietary License
Classifier: Natural Language :: English
Classifier: Operating System :: OS Independent
Classifier: Programming Language :: Python
